CHANGES.txt
LICENSE.txt
README.txt
setup.cfg
setup.py
inquant/__init__.py
inquant.recipe.download.egg-info/PKG-INFO
inquant.recipe.download.egg-info/SOURCES.txt
inquant.recipe.download.egg-info/dependency_links.txt
inquant.recipe.download.egg-info/entry_points.txt
inquant.recipe.download.egg-info/namespace_packages.txt
inquant.recipe.download.egg-info/not-zip-safe
inquant.recipe.download.egg-info/requires.txt
inquant.recipe.download.egg-info/top_level.txt
inquant/recipe/__init__.py
inquant/recipe/download/__init__.py
