Metadata-Version: 1.0
Name: inquant.recipe.download
Version: 0.1.1dev-r1946
Summary: A buildout recipe based on the gocept.download recipe which allows to clean out the destination.
Home-page: https://svn.inquant.de/inquant/develop/plone/recipes/inquant.recipe.download
Author: Stefan Eletzhofer
Author-email: stefan.eletzhofer@inquant.de
License: LGPL
Keywords: buildout recipe
Platform: UNKNOWN
Classifier: Framework :: Buildout
Classifier: Programming Language :: Python
Classifier: Topic :: Software Development :: Libraries :: Python Modules
